src/rc-loss.sv
module rcloss #(
    parameter FEEDBACK = 0,
    parameter KEYLEN = 64, 
    parameter FRAMENUMLEN = 22,
    parameter REGLEN = 0,
    parameter SYNCBITPOS = 0
)(
    input [KEYLEN + FRAMENUMLEN - 1:0] seq,
    input clock,
    input reset,
    output exposed
);
    integer counter;
    reg[REGLEN - 1:0] register;

    assign exposed = register[0];

    always @ (posedge reset) begin
        counter = 0;
        register = {REGLEN {1'b0}};
    end

    always @ (posedge clock) begin
        if (reset) begin
            register[REGLEN - 1] = seq[counter];
        end
    end

    reg rightmost;
    reg[REGLEN:0] shifted;
    always @ (posedge clock) begin
        rightmost = ^(register & FEEDBACK) ^ 1;
        shifted = register << 1;
        register = {shifted[REGLEN - 1:1], rightmost};
    end

endmodule

src/a5-cipher.sv
module cipher #(
    parameter REG1LEN = 19,
    parameter REG2LEN = 22,
    parameter REG3LEN = 23,
    parameter MASK1 = 19'h07200,
    parameter MASK2 = 22'h300000,
    parameter MASK3 = 23'h700100,
    parameter SYNCBIT1 = 8,
    parameter SYNCBIT2 = 10,
    parameter SYNCBIT3 = 10,
    parameter FRAMENUMLEN = 22,
    parameter KEYLEN = 64,
    parameter CHUNKLEN = 114,
    parameter COUNTERLEN = 32
) (
    input in,
    input [FRAMENUMLEN + KEYLEN - 1:0] seq,
    input clock,
    input control,
    input reset,
    output reg out
);
    reg next_clock;

    wire F;
    wire gamma;
    wire outR1;
    wire outR2;
    wire outR3;

    rcloss #(.FEEDBACK(MASK1), .REGLEN(REG1LEN), .SYNCBITPOS(SYNCBIT1)) loss1 (
        .seq(seq),
        .clock(next_clock),
        .reset(reset),
        .exposed(outR1)
    );

    rcloss #(.FEEDBACK(MASK2), .REGLEN(REG2LEN), .SYNCBITPOS(SYNCBIT2)) loss2 (
        .seq(seq),
        .clock(next_clock),
        .reset(reset),
        .exposed(outR2)
    );

    rcloss #(.FEEDBACK(MASK3), .REGLEN(REG3LEN), .SYNCBITPOS(SYNCBIT3)) loss3 (
        .seq(seq),
        .clock(next_clock),
        .reset(reset),
        .exposed(outR3)
    );

    assign gamma = outR1 ^ outR2 ^ outR3;
    assign F = outR1 & outR2 | outR1 & outR3 | outR2 & outR3;

    always @ (clock) begin
        next_clock = 0;
    end

    always @ (clock) begin
        out = (control && !reset) ? in ^ gamma : 0;
    end

    always @ (clock) begin
        next_clock = clock;
    end

endmodule

testbench/testbench.sv
`timescale 1ns / 100ps

module testbench;

    parameter REG1LEN = 19;
    parameter REG2LEN = 22;
    parameter REG3LEN = 23;
    parameter CHUNKLEN = 114;

    parameter MASK1 = 19'h72000;
    parameter MASK2 = 22'h300000;
    parameter MASK3 = 23'h700100;

    parameter KEYLEN = 64;
    parameter FRAMELEN = 22;

    integer j = 0;

    // control units
    reg clock = 0;
    reg control = 0;
    reg reset = 0;

    // input and output data
    reg i;
    wire o;
    reg[CHUNKLEN - 1:0] out = {CHUNKLEN {1'b0}};
    reg[CHUNKLEN - 1:0] in = {CHUNKLEN {1'b0}};

    // key & frame (suppose 2)
    reg[KEYLEN - 1:0] key = 64'h1223456789ABCDEF;
    reg[FRAMELEN - 1:0] frame = 22'h2;

    cipher #(
        .REG1LEN(REG1LEN),
        .REG2LEN(REG2LEN),
        .REG3LEN(REG3LEN),
        .CHUNKLEN(CHUNKLEN),
        .MASK1(MASK1),
        .MASK2(MASK2),
        .MASK3(MASK3)
    ) uut (
        .in(i),
        .seq({key, frame}),
        .clock(clock),
        .control(control),
        .reset(reset),
        .out(o)
    );

    parameter INITRUN = 86;
    parameter DRYRUN = 100;

    initial begin

        // init run (86 ticks)
        reset = 1;
        for (j = 0; j < INITRUN; j = j + 1) begin
            clock = 1;
            #5;
            clock = 0;
        end

        // dry run
        reset = 0;
        for (j = 0; j < DRYRUN; j = j + 1) begin
            clock = 1;
            #5;
            clock = 0;
        end

        // actual cypher
        control = 1;
        for (j = 0; j < CHUNKLEN; j = j + 1) begin
            $display("running iteration: bit in: %d", in[j]);
            i = in[j];
            clock = 1;
            #5;
            $display("bit out: %d", o);
            out[j] = o;
            clock = 0;
        end

        $display("0x%01h_%04h_%04h_%04h_%04h_%04h_%04h_%04h", out[113:110], out[109:96], out[95:80], out[79:64], out[63:48], out[47:32], out[31:16], out[15:0]);
    end

    initial
        $dumpvars;

endmodule

dump.vcd
$date
	Sun Nov 10 19:15:43 2024
$end
$version
	Icarus Verilog
$end
$timescale
	100ps
$end
$scope module testbench $end
$var wire 1 ! o $end
$var parameter 32 " CHUNKLEN $end
$var parameter 32 # DRYRUN $end
$var parameter 32 $ FRAMELEN $end
$var parameter 32 % INITRUN $end
$var parameter 32 & KEYLEN $end
$var parameter 19 ' MASK1 $end
$var parameter 22 ( MASK2 $end
$var parameter 23 ) MASK3 $end
$var parameter 32 * REG1LEN $end
$var parameter 32 + REG2LEN $end
$var parameter 32 , REG3LEN $end
$var reg 1 - clock $end
$var reg 1 . control $end
$var reg 22 / frame [21:0] $end
$var reg 1 0 i $end
$var reg 114 1 in [113:0] $end
$var reg 64 2 key [63:0] $end
$var reg 114 3 out [113:0] $end
$var reg 1 4 reset $end
$var integer 32 5 j [31:0] $end
$scope module uut $end
$var wire 1 6 F $end
$var wire 1 - clock $end
$var wire 1 . control $end
$var wire 1 7 gamma $end
$var wire 1 0 in $end
$var wire 1 4 reset $end
$var wire 86 8 seq [85:0] $end
$var wire 1 9 outR3 $end
$var wire 1 : outR2 $end
$var wire 1 ; outR1 $end
$var parameter 32 < CHUNKLEN $end
$var parameter 32 = COUNTERLEN $end
$var parameter 32 > FRAMENUMLEN $end
$var parameter 32 ? KEYLEN $end
$var parameter 19 @ MASK1 $end
$var parameter 22 A MASK2 $end
$var parameter 23 B MASK3 $end
$var parameter 32 C REG1LEN $end
$var parameter 32 D REG2LEN $end
$var parameter 32 E REG3LEN $end
$var parameter 32 F SYNCBIT1 $end
$var parameter 32 G SYNCBIT2 $end
$var parameter 32 H SYNCBIT3 $end
$var reg 1 I next_clock $end
$var reg 1 ! out $end
$scope module loss1 $end
$var wire 1 I clock $end
$var wire 1 4 reset $end
$var wire 86 J seq [85:0] $end
$var wire 1 ; exposed $end
$var parameter 19 K FEEDBACK $end
$var parameter 32 L FRAMENUMLEN $end
$var parameter 32 M KEYLEN $end
$var parameter 32 N REGLEN $end
$var parameter 32 O SYNCBITPOS $end
$var reg 19 P register [18:0] $end
$var reg 1 Q rightmost $end
$var reg 20 R shifted [19:0] $end
$var integer 32 S counter [31:0] $end
$upscope $end
$scope module loss2 $end
$var wire 1 I clock $end
$var wire 1 4 reset $end
$var wire 86 T seq [85:0] $end
$var wire 1 : exposed $end
$var parameter 22 U FEEDBACK $end
$var parameter 32 V FRAMENUMLEN $end
$var parameter 32 W KEYLEN $end
$var parameter 32 X REGLEN $end
$var parameter 32 Y SYNCBITPOS $end
$var reg 22 Z register [21:0] $end
$var reg 1 [ rightmost $end
$var reg 23 \ shifted [22:0] $end
$var integer 32 ] counter [31:0] $end
$upscope $end
$scope module loss3 $end
$var wire 1 I clock $end
$var wire 1 4 reset $end
$var wire 86 ^ seq [85:0] $end
$var wire 1 9 exposed $end
$var parameter 23 _ FEEDBACK $end
$var parameter 32 ` FRAMENUMLEN $end
$var parameter 32 a KEYLEN $end
$var parameter 32 b REGLEN $end
$var parameter 32 c SYNCBITPOS $end
$var reg 23 d register [22:0] $end
$var reg 1 e rightmost $end
$var reg 24 f shifted [23:0] $end
$var integer 32 g counter [31:0] $end
$upscope $end
$upscope $end
$upscope $end
$enddefinitions $end
$comment Show the parameter values. $end
$dumpall
b1010 c
b10111 b
b1000000 a
b10110 `
b11100000000000100000000 _
b1010 Y
b10110 X
b1000000 W
b10110 V
b1100000000000000000000 U
b1000 O
b10011 N
b1000000 M
b10110 L
b1110010000000000000 K
b1010 H
b1010 G
b1000 F
b10111 E
b10110 D
b10011 C
b11100000000000100000000 B
b1100000000000000000000 A
b1110010000000000000 @
b1000000 ?
b10110 >
b100000 =
b1110010 <
b10111 ,
b10110 +
b10011 *
b11100000000000100000000 )
b1100000000000000000000 (
b1110010000000000000 '
b1000000 &
b1010110 %
b10110 $
b1100100 #
b1110010 "
$end
#0
$dumpvars
b0 g
b0 f
1e
b1 d
b10010001000110100010101100111100010011010101111001101111011110000000000000000000010 ^
b0 ]
b0 \
1[
b1 Z
b10010001000110100010101100111100010011010101111001101111011110000000000000000000010 T
b0 S
b0 R
1Q
b1 P
b10010001000110100010101100111100010011010101111001101111011110000000000000000000010 J
1I
1;
1:
19
b10010001000110100010101100111100010011010101111001101111011110000000000000000000010 8
17
16
b0 5
14
b0 3
b1001000100011010001010110011110001001101010111100110111101111 2
b0 1
x0
b10 /
0.
1-
0!
$end
#50
0I
b1 5
1-
#100
b11 d
b10 f
b11 Z
b10 \
b11 P
b10 R
1I
b10 5
1-
#150
0I
b11 5
1-
#200
b111 P
b110 R
b111 Z
b110 \
b111 d
b110 f
1I
b100 5
1-
#250
0I
b101 5
1-
#300
b1111 d
b1110 f
b1111 Z
b1110 \
b1111 P
b1110 R
1I
b110 5
1-
#350
0I
b111 5
1-
#400
b11111 P
b11110 R
b11111 Z
b11110 \
b11111 d
b11110 f
1I
b1000 5
1-
#450
0I
b1001 5
1-
#500
b111111 d
b111110 f
b111111 Z
b111110 \
b111111 P
b111110 R
1I
b1010 5
1-
#550
0I
b1011 5
1-
#600
b1111111 P
b1111110 R
b1111111 Z
b1111110 \
b1111111 d
b1111110 f
1I
b1100 5
1-
#650
0I
b1101 5
1-
#700
b11111111 d
b11111110 f
b11111111 Z
b11111110 \
b11111111 P
b11111110 R
1I
b1110 5
1-
#750
0I
b1111 5
1-
#800
b111111111 P
b111111110 R
b111111111 Z
b111111110 \
b111111111 d
b111111110 f
1I
b10000 5
1-
#850
0I
b10001 5
1-
#900
07
09
b1111111110 d
b1111111110 f
0e
b1111111111 Z
b1111111110 \
b1111111111 P
b1111111110 R
1I
b10010 5
1-
#950
0I
b10011 5
1-
#1000
b11111111111 P
b11111111110 R
b11111111111 Z
b11111111110 \
b11111111100 d
b11111111100 f
1I
b10100 5
1-
#1050
0I
b10101 5
1-
#1100
b111111111000 d
b111111111000 f
b111111111111 Z
b111111111110 \
b111111111111 P
b111111111110 R
1I
b10110 5
1-
#1150
0I
b10111 5
1-
#1200
b1111111111111 P
b1111111111110 R
b1111111111111 Z
b1111111111110 \
b1111111110000 d
b1111111110000 f
1I
b11000 5
1-
#1250
0I
b11001 5
1-
#1300
b11111111100000 d
b11111111100000 f
b11111111111111 Z
b11111111111110 \
b11111111111111 P
b11111111111110 R
1I
b11010 5
1-
#1350
0I
b11011 5
1-
#1400
06
17
0;
b111111111111110 P
b111111111111110 R
0Q
b111111111111111 Z
b111111111111110 \
b111111111000000 d
b111111111000000 f
1I
b11100 5
1-
#1450
0I
b11101 5
1-
#1500
b1111111110000000 d
b1111111110000000 f
b1111111111111111 Z
b1111111111111110 \
b1111111111111100 P
b1111111111111100 R
1I
b11110 5
1-
#1550
0I
b11111 5
1-
#1600
b11111111111111000 P
b11111111111111000 R
b11111111111111111 Z
b11111111111111110 \
b11111111100000000 d
b11111111100000000 f
1I
b100000 5
1-
#1650
0I
b100001 5
1-
#1700
16
07
1;
b111111111000000000 d
b111111111000000000 f
b111111111111111111 Z
b111111111111111110 \
b111111111111110001 P
b111111111111110000 R
1Q
1I
b100010 5
1-
#1750
0I
b100011 5
1-
#1800
07
0;
19
b111111111111100010 P
b1111111111111100010 R
0Q
b1111111111111111111 Z
b1111111111111111110 \
b1111111110000000001 d
b1111111110000000000 f
1e
1I
b100100 5
1-
#1850
0I
b100101 5
1-
#1900
b11111111100000000011 d
b11111111100000000010 f
b11111111111111111111 Z
b11111111111111111110 \
b1111111111111000100 P
b1111111111111000100 R
1I
b100110 5
1-
#1950
0I
b100111 5
1-
#2000
17
1;
b111111111110001001 P
b11111111111110001000 R
1Q
b111111111111111111111 Z
b111111111111111111110 \
b111111111000000000111 d
b111111111000000000110 f
1I
b101000 5
1-
#2050
0I
b101001 5
1-
#2100
06
07
09
0:
0;
b1111111110000000001110 d
b1111111110000000001110 f
0e
b1111111111111111111110 Z
b1111111111111111111110 \
0[
b1111111111100010010 P
b1111111111100010010 R
0Q
1I
b101010 5
1-
#2150
0I
b101011 5
1-
#2200
16
17
1;
1:
19
b111111111000100101 P
b11111111111000100100 R
1Q
b111111111111111111101 Z
b11111111111111111111100 \
1[
b1111111100000000011101 d
b11111111100000000011100 f
1e
1I
b101100 5
1-
#2250
0I
b101101 5
1-
#2300
06
0:
0;
b11111111000000000111011 d
b11111111000000000111010 f
b1111111111111111111010 Z
b1111111111111111111010 \
0[
b1111111110001001010 P
b1111111110001001010 R
0Q
1I
b101110 5
1-
#2350
0I
b101111 5
1-
#2400
16
07
1;
1:
09
b111111100010010101 P
b11111111100010010100 R
1Q
b111111111111111110101 Z
b11111111111111111110100 \
1[
b1111110000000001110110 d
b111111110000000001110110 f
0e
1I
b110000 5
1-
#2450
0I
b110001 5
1-
#2500
06
17
19
0:
0;
b11111100000000011101101 d
b11111100000000011101100 f
1e
b1111111111111111101010 Z
b1111111111111111101010 \
0[
b1111111000100101010 P
b1111111000100101010 R
0Q
1I
b110010 5
1-
#2550
0I
b110011 5
1-
#2600
16
07
1;
1:
09
b111110001001010101 P
b11111110001001010100 R
1Q
b111111111111111010101 Z
b11111111111111111010100 \
1[
b1111000000000111011010 d
b111111000000000111011010 f
0e
1I
b110100 5
1-
#2650
0I
b110101 5
1-
#2700
06
0:
0;
b11110000000001110110100 d
b11110000000001110110100 f
b1111111111111110101010 Z
b1111111111111110101010 \
0[
b1111100010010101010 P
b1111100010010101010 R
0Q
1I
b110110 5
1-
#2750
0I
b110111 5
1-
#2800
16
07
1:
19
b111000100101010100 P
b11111000100101010100 R
b111111111111101010101 Z
b11111111111111101010100 \
1[
b1100000000011101101001 d
b111100000000011101101000 f
1e
1I
b111000 5
1-
#2850
0I
b111001 5
1-
#2900
06
17
09
0:
1;
b11000000000111011010010 d
b11000000000111011010010 f
0e
b1111111111111010101010 Z
b1111111111111010101010 \
0[
b1110001001010101001 P
b1110001001010101000 R
1Q
1I
b111010 5
1-
#2950
0I
b111011 5
1-
#3000
16
07
0;
1:
19
b100010010101010010 P
b11100010010101010010 R
0Q
b111111111110101010101 Z
b11111111111110101010100 \
1[
b1110110100101 d
b110000000001110110100100 f
1e
1I
b111100 5
1-
#3050
0I
b111101 5
1-
#3100
06
17
09
0:
1;
b11101101001010 d
b11101101001010 f
0e
b1111111111101010101010 Z
b1111111111101010101010 \
0[
b1000100101010100101 P
b1000100101010100100 R
1Q
1I
b111110 5
1-
#3150
0I
b111111 5
1-
#3200
0;
1:
b1001010101001010 P
b10001001010101001010 R
0Q
b111111111010101010101 Z
b11111111111010101010100 \
1[
b111011010010100 d
b111011010010100 f
1I
b1000000 5
1-
#3250
0I
b1000001 5
1-
#3300
16
07
19
0:
1;
b1110110100101001 d
b1110110100101000 f
1e
b1111111110101010101010 Z
b1111111110101010101010 \
0[
b10010101010010101 P
b10010101010010100 R
1Q
1I
b1000010 5
1-
#3350
0I
b1000011 5
1-
#3400
07
1:
09
b100101010100101011 P
b100101010100101010 R
b111111101010101010101 Z
b11111111101010101010100 \
1[
b11101101001010010 d
b11101101001010010 f
0e
1I
b1000100 5
1-
#3450
0I
b1000101 5
1-
#3500
06
17
19
0:
0;
b111011010010100101 d
b111011010010100100 f
1e
b1111111010101010101010 Z
b1111111010101010101010 \
0[
b1001010101001010110 P
b1001010101001010110 R
0Q
1I
b1000110 5
1-
#3550
0I
b1000111 5
1-
#3600
16
1;
1:
b10101010010101101 P
b10010101010010101100 R
1Q
b111110101010101010101 Z
b11111110101010101010100 \
1[
b1110110100101001011 d
b1110110100101001010 f
1I
b1001000 5
1-
#3650
0I
b1001001 5
1-
#3700
06
07
09
0:
0;
b11101101001010010110 d
b11101101001010010110 f
0e
b1111101010101010101010 Z
b1111101010101010101010 \
0[
b101010100101011010 P
b101010100101011010 R
0Q
1I
b1001010 5
1-
#3750
0I
b1001011 5
1-
#3800
16
17
1;
1:
19
b10101001010110101 P
b1010101001010110100 R
1Q
b111010101010101010101 Z
b11111010101010101010100 \
1[
b111011010010100101101 d
b111011010010100101100 f
1e
1I
b1001100 5
1-
#3850
0I
b1001101 5
1-
#3900
06
0:
0;
b1110110100101001011011 d
b1110110100101001011010 f
b1110101010101010101010 Z
b1110101010101010101010 \
0[
b101010010101101010 P
b101010010101101010 R
0Q
1I
b1001110 5
1-
#3950
0I
b1001111 5
1-
#4000
16
1;
1:
b10100101011010101 P
b1010100101011010100 R
1Q
b101010101010101010101 Z
b11101010101010101010100 \
1[
b1101101001010010110111 d
b11101101001010010110110 f
1I
b1010000 5
1-
#4050
0I
b1010001 5
1-
#4100
06
0:
0;
b11011010010100101101111 d
b11011010010100101101110 f
b1010101010101010101010 Z
b1010101010101010101010 \
0[
b101001010110101010 P
b101001010110101010 R
0Q
1I
b1010010 5
1-
#4150
0I
b1010011 5
1-
#4200
07
09
b10010101101010100 P
b1010010101101010100 R
b101010101010101010100 Z
b10101010101010101010100 \
b110100101001011011110 d
b110110100101001011011110 f
0e
1I
b1010100 5
1-
#4250
0I
b1010101 5
1-
#4300
17
1;
b1101001010010110111100 d
b1101001010010110111100 f
b1010101010101010101000 Z
b1010101010101010101000 \
b100101011010101001 P
b100101011010101000 R
1Q
1I
04
b0 5
1-
#4350
0I
b1 5
1-
#4400
07
0;
b1001010110101010010 P
b1001010110101010010 R
0Q
b101010101010101010000 Z
b10101010101010101010000 \
b11010010100101101111000 d
b11010010100101101111000 f
1I
b10 5
1-
#4450
0I
b11 5
1-
#4500
17
1;
b10100101001011011110000 d
b110100101001011011110000 f
b1010101010101010100000 Z
b1010101010101010100000 \
b10101101010100101 P
b10010101101010100100 R
1Q
1I
b100 5
1-
#4550
0I
b101 5
1-
#4600
17
0;
19
b101011010101001010 P
b101011010101001010 R
0Q
b101010101010101000000 Z
b10101010101010101000000 \
b1001010010110111100001 d
b101001010010110111100000 f
1e
1I
b110 5
1-
#4650
0I
b111 5
1-
#4700
16
07
1;
b10010100101101111000011 d
b10010100101101111000010 f
b1010101010101010000000 Z
b1010101010101010000000 \
b1010110101010010101 P
b1010110101010010100 R
1Q
1I
b1000 5
1-
#4750
0I
b1001 5
1-
#4800
06
17
0;
b101101010100101010 P
b10101101010100101010 R
0Q
b101010101010100000000 Z
b10101010101010100000000 \
b101001011011110000111 d
b100101001011011110000110 f
1I
b1010 5
1-
#4850
0I
b1011 5
1-
#4900
b1010010110111100001111 d
b1010010110111100001110 f
b1010101010101000000000 Z
b1010101010101000000000 \
b1011010101001010100 P
b1011010101001010100 R
1I
b1100 5
1-
#4950
0I
b1101 5
1-
#5000
b110101010010101000 P
b10110101010010101000 R
b101010101010000000000 Z
b10101010101010000000000 \
b10100101101111000011111 d
b10100101101111000011110 f
1I
b1110 5
1-
#5050
0I
b1111 5
1-
#5100
16
07
1;
b1001011011110000111111 d
b101001011011110000111110 f
b1010101010100000000000 Z
b1010101010100000000000 \
b1101010100101010001 P
b1101010100101010000 R
1Q
1I
b10000 5
1-
#5150
0I
b10001 5
1-
#5200
06
07
0;
09
b1010101001010100010 P
b11010101001010100010 R
0Q
b101010101000000000000 Z
b10101010101000000000000 \
b10010110111100001111110 d
b10010110111100001111110 f
0e
1I
b10010 5
1-
#5250
0I
b10011 5
1-
#5300
17
1;
b101101111000011111100 d
b100101101111000011111100 f
b1010101010000000000000 Z
b1010101010000000000000 \
b101010010101000101 P
b10101010010101000100 R
1Q
1I
b10100 5
1-
#5350
0I
b10101 5
1-
#5400
b1010100101010001011 P
b1010100101010001010 R
b101010100000000000000 Z
b10101010100000000000000 \
b1011011110000111111000 d
b1011011110000111111000 f
1I
b10110 5
1-
#5450
0I
b10111 5
1-
#5500
16
07
19
b10110111100001111110001 d
b10110111100001111110000 f
1e
b1010101000000000000000 Z
b1010101000000000000000 \
b101001010100010111 P
b10101001010100010110 R
1I
b11000 5
1-
#5550
0I
b11001 5
1-
#5600
06
07
0;
09
b1010010101000101110 P
b1010010101000101110 R
0Q
b101010000000000000000 Z
b10101010000000000000000 \
b1101111000011111100010 d
b101101111000011111100010 f
0e
1I
b11010 5
1-
#5650
0I
b11011 5
1-
#5700
b11011110000111111000100 d
b11011110000111111000100 f
b1010100000000000000000 Z
b1010100000000000000000 \
b100101010001011100 P
b10100101010001011100 R
1I
b11100 5
1-
#5750
0I
b11101 5
1-
#5800
b1001010100010111000 P
b1001010100010111000 R
b101000000000000000000 Z
b10101000000000000000000 \
b10111100001111110001000 d
b110111100001111110001000 f
1I
b11110 5
1-
#5850
0I
b11111 5
1-
#5900
17
1;
b1111000011111100010000 d
b101111000011111100010000 f
b1010000000000000000000 Z
b1010000000000000000000 \
b10101000101110001 P
b10010101000101110000 R
1Q
1I
b100000 5
1-
#5950
0I
b100001 5
1-
#6000
07
0;
b101010001011100010 P
b101010001011100010 R
0Q
b100000000000000000000 Z
b10100000000000000000000 \
b11110000111111000100000 d
b11110000111111000100000 f
1I
b100010 5
1-
#6050
0I
b100011 5
1-
#6100
17
1;
b11100001111110001000000 d
b111100001111110001000000 f
b1000000000000000000000 Z
b1000000000000000000000 \
b1010100010111000101 P
b1010100010111000100 R
1Q
1I
b100100 5
1-
#6150
0I
b100101 5
1-
#6200
b101000101110001011 P
b10101000101110001010 R
b0 Z
b10000000000000000000000 \
b11000011111100010000000 d
b111000011111100010000000 f
1I
b100110 5
1-
#6250
0I
b100111 5
1-
#6300
16
07
19
1:
0;
b10000111111000100000001 d
b110000111111000100000000 f
1e
b1 Z
b0 \
1[
b1010001011100010110 P
b1010001011100010110 R
0Q
1I
b101000 5
1-
#6350
0I
b101001 5
1-
#6400
17
1;
b100010111000101101 P
b10100010111000101100 R
1Q
b11 Z
b10 \
b1111110001000000011 d
b100001111110001000000010 f
1I
b101010 5
1-
#6450
0I
b101011 5
1-
#6500
b11111100010000000111 d
b11111100010000000110 f
b111 Z
b110 \
b1000101110001011011 P
b1000101110001011010 R
1I
b101100 5
1-
#6550
0I
b101101 5
1-
#6600
07
0;
b1011100010110110 P
b10001011100010110110 R
0Q
b1111 Z
b1110 \
b111111000100000001111 d
b111111000100000001110 f
1I
b101110 5
1-
#6650
0I
b101111 5
1-
#6700
06
17
09
b1111110001000000011110 d
b1111110001000000011110 f
0e
b11111 Z
b11110 \
b10111000101101100 P
b10111000101101100 R
1I
b110000 5
1-
#6750
0I
b110001 5
1-
#6800
16
17
1;
19
b101110001011011001 P
b101110001011011000 R
1Q
b111111 Z
b111110 \
b11111100010000000111101 d
b11111100010000000111100 f
1e
1I
b110010 5
1-
#6850
0I
b110011 5
1-
#6900
07
09
b11111000100000001111010 d
b111111000100000001111010 f
0e
b1111111 Z
b1111110 \
b1011100010110110011 P
b1011100010110110010 R
1I
b110100 5
1-
#6950
0I
b110101 5
1-
#7000
b111000101101100111 P
b10111000101101100110 R
b11111111 Z
b11111110 \
b11110001000000011110100 d
b111110001000000011110100 f
1I
b110110 5
1-
#7050
0I
b110111 5
1-
#7100
b11100010000000111101000 d
b111100010000000111101000 f
b111111111 Z
b111111110 \
b1110001011011001111 P
b1110001011011001110 R
1I
b111000 5
1-
#7150
0I
b111001 5
1-
#7200
07
0;
19
b1100010110110011110 P
b11100010110110011110 R
0Q
b1111111111 Z
b1111111110 \
b11000100000001111010001 d
b111000100000001111010000 f
1e
1I
b111010 5
1-
#7250
0I
b111011 5
1-
#7300
06
17
09
b10001000000011110100010 d
b110001000000011110100010 f
0e
b11111111111 Z
b11111111110 \
b1000101101100111100 P
b11000101101100111100 R
1I
b111100 5
1-
#7350
0I
b111101 5
1-
#7400
16
07
19
b1011011001111000 P
b10001011011001111000 R
b111111111111 Z
b111111111110 \
b10000000111101000101 d
b100010000000111101000100 f
1e
1I
b111110 5
1-
#7450
0I
b111111 5
1-
#7500
06
17
09
b100000001111010001010 d
b100000001111010001010 f
0e
b1111111111111 Z
b1111111111110 \
b10110110011110000 P
b10110110011110000 R
1I
b1000000 5
1-
#7550
0I
b1000001 5
1-
#7600
16
07
1;
b101101100111100001 P
b101101100111100000 R
1Q
b11111111111111 Z
b11111111111110 \
b1000000011110100010100 d
b1000000011110100010100 f
1I
b1000010 5
1-
#7650
0I
b1000011 5
1-
#7700
19
0;
b10000000111101000101001 d
b10000000111101000101000 f
1e
b111111111111111 Z
b111111111111110 \
b1011011001111000010 P
b1011011001111000010 R
0Q
1I
b1000100 5
1-
#7750
0I
b1000101 5
1-
#7800
06
17
09
b110110011110000100 P
b10110110011110000100 R
b1111111111111111 Z
b1111111111111110 \
b1111010001010010 d
b100000001111010001010010 f
0e
1I
b1000110 5
1-
#7850
0I
b1000111 5
1-
#7900
16
07
19
b11110100010100101 d
b11110100010100100 f
1e
b11111111111111111 Z
b11111111111111110 \
b1101100111100001000 P
b1101100111100001000 R
1I
b1001000 5
1-
#7950
0I
b1001001 5
1-
#8000
17
1;
b1011001111000010001 P
b11011001111000010000 R
1Q
b111111111111111111 Z
b111111111111111110 \
b111101000101001011 d
b111101000101001010 f
1I
b1001010 5
1-
#8050
0I
b1001011 5
1-
#8100
07
09
b1111010001010010110 d
b1111010001010010110 f
0e
b1111111111111111111 Z
b1111111111111111110 \
b110011110000100011 P
b10110011110000100010 R
1I
b1001100 5
1-
#8150
0I
b1001101 5
1-
#8200
07
0;
19
b1100111100001000110 P
b1100111100001000110 R
0Q
b11111111111111111111 Z
b11111111111111111110 \
b11110100010100101101 d
b11110100010100101100 f
1e
1I
b1001110 5
1-
#8250
0I
b1001111 5
1-
#8300
06
17
09
b111101000101001011010 d
b111101000101001011010 f
0e
b111111111111111111111 Z
b111111111111111111110 \
b1001111000010001100 P
b11001111000010001100 R
1I
b1010000 5
1-
#8350
0I
b1010001 5
1-
#8400
1;
0:
b11110000100011001 P
b10011110000100011000 R
1Q
b1111111111111111111110 Z
b1111111111111111111110 \
0[
b1111010001010010110100 d
b1111010001010010110100 f
1I
b1010010 5
1-
#8450
0I
b1010011 5
1-
#8500
16
19
1:
b11110100010100101101001 d
b11110100010100101101000 f
1e
b1111111111111111111101 Z
b11111111111111111111100 \
1[
b111100001000110011 P
b111100001000110010 R
1I
b1010100 5
1-
#8550
0I
b1010101 5
1-
#8600
b1111000010001100111 P
b1111000010001100110 R
b1111111111111111111011 Z
b11111111111111111111010 \
b11101000101001011010011 d
b111101000101001011010010 f
1I
b1010110 5
1-
#8650
0I
b1010111 5
1-
#8700
06
09
0;
b11010001010010110100110 d
b111010001010010110100110 f
0e
b1111111111111111110111 Z
b11111111111111111110110 \
b1110000100011001110 P
b11110000100011001110 R
0Q
1I
b1011000 5
1-
#8750
0I
b1011001 5
1-
#8800
b1100001000110011100 P
b11100001000110011100 R
b1111111111111111101111 Z
b11111111111111111101110 \
b10100010100101101001100 d
b110100010100101101001100 f
1I
b1011010 5
1-
#8850
0I
b1011011 5
1-
#8900
16
07
1;
b1000101001011010011000 d
b101000101001011010011000 f
b1111111111111111011111 Z
b11111111111111111011110 \
b1000010001100111001 P
b11000010001100111000 R
1Q
1I
b1011100 5
1-
#8950
0I
b1011101 5
1-
#9000
b100011001110011 P
b10000100011001110010 R
b1111111111111110111111 Z
b11111111111111110111110 \
b10001010010110100110000 d
b10001010010110100110000 f
1I
b1011110 5
1-
#9050
0I
b1011111 5
1-
#9100
17
19
b10100101101001100001 d
b100010100101101001100000 f
1e
b1111111111111101111111 Z
b11111111111111101111110 \
b1000110011100111 P
b1000110011100110 R
1I
b1100000 5
1-
#9150
0I
b1100001 5
1-
#9200
b10001100111001111 P
b10001100111001110 R
b1111111111111011111111 Z
b11111111111111011111110 \
b101001011010011000011 d
b101001011010011000010 f
1I
b1100010 5
1-
#9250
0I
b1100011 5
1-
#9300
06
09
0;
b1010010110100110000110 d
b1010010110100110000110 f
0e
b1111111111110111111111 Z
b11111111111110111111110 \
b100011001110011110 P
b100011001110011110 R
0Q
1I
1!
00
1.
b0 5
1-
#9350
0I
b1 5
1-
b1 3
#9400
16
17
1;
19
b1000110011100111101 P
b1000110011100111100 R
1Q
b1111111111101111111111 Z
b11111111111101111111110 \
b10100101101001100001101 d
b10100101101001100001100 f
1e
1I
b10 5
1-
b11 3
#9450
0I
b11 5
1-
b111 3
#9500
07
09
b1001011010011000011010 d
b101001011010011000011010 f
0e
b1111111111011111111111 Z
b11111111111011111111110 \
b1100111001111011 P
b10001100111001111010 R
1I
b100 5
1-
b1111 3
#9550
0I
0!
b101 5
1-
b11111 3
#9600
b11001110011110111 P
b11001110011110110 R
b1111111110111111111111 Z
b11111111110111111111110 \
b10010110100110000110100 d
b10010110100110000110100 f
1I
b110 5
1-
#9650
0I
b111 5
1-
#9700
06
17
0;
b101101001100001101000 d
b100101101001100001101000 f
b1111111101111111111111 Z
b11111111101111111111110 \
b110011100111101110 P
b110011100111101110 R
0Q
1I
b1000 5
1-
#9750
0I
1!
b1001 5
1-
#9800
b1100111001111011100 P
b1100111001111011100 R
b1111111011111111111111 Z
b11111111011111111111110 \
b1011010011000011010000 d
b1011010011000011010000 f
1I
b1010 5
1-
b1000011111 3
#9850
0I
b1011 5
1-
b11000011111 3
#9900
b10110100110000110100000 d
b10110100110000110100000 f
b1111110111111111111111 Z
b11111110111111111111110 \
b1001110011110111000 P
b11001110011110111000 R
1I
b1100 5
1-
b111000011111 3
#9950
0I
b1101 5
1-
b1111000011111 3
#10000
16
07
1;
b11100111101110001 P
b10011100111101110000 R
1Q
b1111101111111111111111 Z
b11111101111111111111110 \
b1101001100001101000000 d
b101101001100001101000000 f
1I
b1110 5
1-
b11111000011111 3
#10050
0I
0!
b1111 5
1-
b111111000011111 3
